fusionlab/__init__.py
fusionlab/_fusionlog.py
fusionlab/_util.py
fusionlab/decorators.py
fusionlab/exceptions.py
fusionlab/metrics.py
fusionlab/api/__init__.py
fusionlab/api/bunch.py
fusionlab/api/docs.py
fusionlab/api/property.py
fusionlab/api/summary.py
fusionlab/api/types.py
fusionlab/api/util.py
fusionlab/backends/__init__.py
fusionlab/backends/base.py
fusionlab/backends/cupy.py
fusionlab/backends/dask.py
fusionlab/backends/nn.py
fusionlab/backends/numpy.py
fusionlab/backends/scipy.py
fusionlab/backends/selector.py
fusionlab/compat/__init__.py
fusionlab/compat/numpy.py
fusionlab/compat/pandas.py
fusionlab/compat/scipy.py
fusionlab/compat/sklearn.py
fusionlab/compat/tf.py
fusionlab/compat/types.py
fusionlab/core/__init__.py
fusionlab/core/array_manager.py
fusionlab/core/checks.py
fusionlab/core/diagnose_q.py
fusionlab/core/handlers.py
fusionlab/core/io.py
fusionlab/core/utils.py
fusionlab/datasets/__init__.py
fusionlab/datasets/_property.py
fusionlab/datasets/load.py
fusionlab/datasets/make.py
fusionlab/datasets/data/__init__.py
fusionlab/datasets/data/nansha_2000.csv
fusionlab/datasets/data/zhongshan_2000.csv
fusionlab/nn/__init__.py
fusionlab/nn/_adj_tft.py
fusionlab/nn/_config.py
fusionlab/nn/_forecast_tuner.py
fusionlab/nn/_tensor_validation.py
fusionlab/nn/_tft.py
fusionlab/nn/_wrappers.py
fusionlab/nn/_xtft.py
fusionlab/nn/anomaly_detection.py
fusionlab/nn/components.py
fusionlab/nn/dummies.py
fusionlab/nn/forecast_tuner.py
fusionlab/nn/keras_validator.py
fusionlab/nn/losses.py
fusionlab/nn/physnet.py
fusionlab/nn/transformers.py
fusionlab/nn/tuner.py
fusionlab/nn/utils.py
fusionlab/nn/wrappers.py
fusionlab/plot/__init__.py
fusionlab/plot/_evaluation.py
fusionlab/plot/evaluation.py
fusionlab/plot/forecast.py
fusionlab/tools/__init__.py
fusionlab/tools/tft_batch_p.py
fusionlab/tools/tft_cli.py
fusionlab/tools/xtft_point.py
fusionlab/tools/xtft_proba.py
fusionlab/tools/xtft_proba_p.py
fusionlab/utils/__init__.py
fusionlab/utils/_array_api.py
fusionlab_learn-0.2.3.dist-info/licenses/LICENSE
fusionlab_learn-0.2.3.dist-info/METADATA
fusionlab_learn-0.2.3.dist-info/WHEEL
fusionlab_learn-0.2.3.dist-info/entry_points.txt
fusionlab_learn-0.2.3.dist-info/top_level.txt
fusionlab_learn-0.2.3.dist-info/RECORD
