Metadata-Version: 2.4
Name: fusionlab-learn
Version: 0.2.3
Summary: Next-Gen Temporal Fusion Architectures for Time-Series Forecasting
Home-page: https://github.com/earthai-tech/fusionlab-learn
Author: Laurent Kouadio
Author-email: etanoyau@gmail.com
Maintainer: Laurent Kouadio
Maintainer-email: etanoyau@gmail.com
License: BSD-3-Clause
Keywords: time-series forecasting,machine learning,temporal fusion,deep learning
Classifier: Development Status :: 3 - Alpha
Classifier: Intended Audience :: Science/Research
Classifier: Intended Audience :: Developers
Classifier: Topic :: Software Development
Classifier: Topic :: Scientific/Engineering
Classifier: Programming Language :: Python
Classifier: Programming Language :: Python :: 3.9
Classifier: Programming Language :: Python :: 3.10
Classifier: Programming Language :: Python :: 3.11
Classifier: Programming Language :: Python :: 3.12
Classifier: Operating System :: OS Independent
Requires-Python: >=3.9
License-File: LICENSE
Requires-Dist: numpy<2
Requires-Dist: pandas
Requires-Dist: scipy
Requires-Dist: matplotlib
Requires-Dist: tqdm
Requires-Dist: scikit-learn
Requires-Dist: statsmodels
Requires-Dist: tensorflow>=2.15
Requires-Dist: joblib
Requires-Dist: pyyaml
Provides-Extra: dev
Requires-Dist: pytest; extra == "dev"
Requires-Dist: sphinx; extra == "dev"
Requires-Dist: flake8; extra == "dev"
Provides-Extra: k-diagram
Requires-Dist: k-diagram>=1.0.3; extra == "k-diagram"
Provides-Extra: full
Requires-Dist: pytest; extra == "full"
Requires-Dist: flake8; extra == "full"
Requires-Dist: sphinx; extra == "full"
Requires-Dist: k-diagram>=1.0.3; extra == "full"
Dynamic: author
Dynamic: author-email
Dynamic: classifier
Dynamic: description
Dynamic: description-content-type
Dynamic: home-page
Dynamic: keywords
Dynamic: license
Dynamic: license-file
Dynamic: maintainer
Dynamic: maintainer-email
Dynamic: provides-extra
Dynamic: requires-dist
Dynamic: requires-python
Dynamic: summary
